cse587Autils/DiceObjects/BagOfDice.py
cse587Autils/DiceObjects/Die.py
cse587Autils/DiceObjects/__init__.py
cse587Autils/DiceObjects/test_BagOfDice.py
cse587Autils/DiceObjects/test_Die.py
cse587Autils/SequenceObjects/SequenceModel.py
cse587Autils/SequenceObjects/test_SequenceModel.py
cse587Autils/__init__.py
cse587Autils/configure_logging.py
cse587Autils/utils/__init__.py
cse587Autils/utils/check_probability.py
cse587Autils/utils/euclidean_distance_lists.py
cse587Autils/utils/flatten_2d_list.py
cse587Autils/utils/test_check_probabilities.py
cse587Autils/utils/test_euclidean_distance_lists.py
cse587Autils/utils/test_flatten_2d_list.py
cse587Autils/utils/type_prob_table.py
cse587autils-3.2.1.dist-info/LICENSE
cse587autils-3.2.1.dist-info/METADATA
cse587autils-3.2.1.dist-info/WHEEL
cse587autils-3.2.1.dist-info/RECORD
