Metadata-Version: 2.1
Name: cse587Autils
Version: 3.2.1
Summary: A set of classes and functions to be used in CSE 587A
License: GPL-3.0-or-later
Author: chase mateusiak
Author-email: chase.mateusiak@gmail.com
Requires-Python: >=3.9,<4.0
Classifier: License :: OSI Approved :: GNU General Public License v3 or later (GPLv3+)
Classifier: Programming Language :: Python :: 3
Classifier: Programming Language :: Python :: 3.9
Classifier: Programming Language :: Python :: 3.10
Classifier: Programming Language :: Python :: 3.11
Requires-Dist: numpy (>=1.25.1,<2.0.0)
Requires-Dist: pandas (>=2.0.3,<3.0.0)
